example.py
peppa.py
peppa8.py
peppa8-0.1.1.dist-info/LICENSE
peppa8-0.1.1.dist-info/METADATA
peppa8-0.1.1.dist-info/WHEEL
peppa8-0.1.1.dist-info/entry_points.txt
peppa8-0.1.1.dist-info/top_level.txt
peppa8-0.1.1.dist-info/RECORD
