Metadata-Version: 2.1
Name: peppa8
Version: 0.1.1
Summary: UNKNOWN
Home-page: https://github.com/skhortiuk/peppa8
Author: Serhii Khortiuk
Author-email: khortiukserhii@ukr.net
License: MIT
Platform: UNKNOWN
Requires-Dist: autopep8
